mcp_json_yaml_toml/AGENTS.md
mcp_json_yaml_toml/__init__.py
mcp_json_yaml_toml/config.py
mcp_json_yaml_toml/default_schema_stores.json
mcp_json_yaml_toml/lmql_constraints.py
mcp_json_yaml_toml/py.typed
mcp_json_yaml_toml/schemas.py
mcp_json_yaml_toml/server.py
mcp_json_yaml_toml/toml_utils.py
mcp_json_yaml_toml/version.py
mcp_json_yaml_toml/yaml_optimizer.py
mcp_json_yaml_toml/yq_wrapper.py
mcp_json_yaml_toml/tests/__init__.py
mcp_json_yaml_toml/tests/conftest.py
mcp_json_yaml_toml/tests/mcp_protocol_client.py
mcp_json_yaml_toml/tests/test_config.py
mcp_json_yaml_toml/tests/test_fastmcp_integration.py
mcp_json_yaml_toml/tests/test_lmql_constraints.py
mcp_json_yaml_toml/tests/test_no_anchor_files.py
mcp_json_yaml_toml/tests/test_pagination.py
mcp_json_yaml_toml/tests/test_schema_detection.py
mcp_json_yaml_toml/tests/test_schemas.py
mcp_json_yaml_toml/tests/test_server.py
mcp_json_yaml_toml/tests/test_set_type_preservation.py
mcp_json_yaml_toml/tests/test_toml_formatting.py
mcp_json_yaml_toml/tests/test_toml_write.py
mcp_json_yaml_toml/tests/test_yaml_optimization_integration.py
mcp_json_yaml_toml/tests/test_yaml_optimizer.py
mcp_json_yaml_toml/tests/test_yq_wrapper.py
mcp_json_yaml_toml/tests/verify_features.py
mcp_json_yaml_toml-0.8.0.dist-info/METADATA
mcp_json_yaml_toml-0.8.0.dist-info/WHEEL
mcp_json_yaml_toml-0.8.0.dist-info/entry_points.txt
mcp_json_yaml_toml-0.8.0.dist-info/licenses/LICENSE
mcp_json_yaml_toml-0.8.0.dist-info/RECORD
