Metadata-Version: 2.4
Name: mcp-json-yaml-toml
Version: 0.8.0
Summary: MCP server for querying and modifying JSON, YAML, and TOML files using yq
Project-URL: Homepage, https://github.com/bitflight-devops/mcp-json-yaml-toml
Project-URL: Repository, https://github.com/bitflight-devops/mcp-json-yaml-toml
Project-URL: Issues, https://github.com/bitflight-devops/mcp-json-yaml-toml/issues
Author-email: Jamie Nelson <jamie@bitflight.io>
Maintainer-email: Jamie Nelson <jamie@bitflight.io>
License: MIT
License-File: LICENSE
Keywords: json,mcp,mcp-server,model-context-protocol,toml,yaml,yq
Classifier: Development Status :: 4 - Beta
Classifier: Intended Audience :: Developers
Classifier: License :: OSI Approved :: MIT License
Classifier: Operating System :: POSIX :: Linux
Classifier: Programming Language :: Python :: 3
Classifier: Programming Language :: Python :: 3.11
Classifier: Programming Language :: Python :: 3.12
Classifier: Topic :: Software Development :: Libraries :: Python Modules
Requires-Python: <3.15,>=3.11
Requires-Dist: fastmcp<3,>=2.14.4
Requires-Dist: httpx>=0.28.1
Requires-Dist: json-strong-typing>=0.4.3
Requires-Dist: jsonschema>=4.26.0
Requires-Dist: lmql>=0.7.3
Requires-Dist: orjson>=3.11.6
Requires-Dist: portalocker>=3.1.1
Requires-Dist: ruamel-yaml>=0.18.0
Requires-Dist: tomlkit>=0.14.0
